ganondorf/__init__.py
ganpy-0.0.1.dist-info/METADATA
ganpy-0.0.1.dist-info/WHEEL
ganpy-0.0.1.dist-info/top_level.txt
ganpy-0.0.1.dist-info/RECORD
