Metadata-Version: 2.1
Name: ganpy
Version: 0.0.1
Summary: A Gan Medical Image Segmentation Federated Learning Framework
Home-page: UNKNOWN
Author: James Calo
Author-email: jamesafcalo@gmail.com
License: UNKNOWN
Platform: UNKNOWN
Classifier: Programming Language :: Python :: 3.8
Classifier: License :: OSI Approved :: GNU General Public License v3 (GPLv3)
Classifier: Operating System :: OS Independent
Requires-Python: !=3.9.*,>=3.8
Requires-Dist: tensorflow
Requires-Dist: tensorflow-federated (<1.0.0,>=0.17.0)
Requires-Dist: matplotlib
